attrdict/__init__.py
attrdict/_base.py
attrdict/_base_utils.py
attrdict/test.py
attrdict/utils.py
attr_dicts-1.0.3.dist-info/METADATA
attr_dicts-1.0.3.dist-info/WHEEL
attr_dicts-1.0.3.dist-info/licenses/LICENSE
attr_dicts-1.0.3.dist-info/RECORD
