Metadata-Version: 2.3
Name: attr-dicts
Version: 1.0.3
Summary: AttrDict for nested dictionary processing and utilities
Project-URL: Homepage, https://github.com/Stanford-ILIAD/attrdict
Project-URL: Bug Tracker, https://github.com/Stanford-ILIAD/attrdict/issues
Author-email: Suneel Belkhale <belkhale@stanford.edu>
License-File: LICENSE
Classifier: License :: OSI Approved :: MIT License
Classifier: Operating System :: OS Independent
Classifier: Programming Language :: Python :: 3
Requires-Python: >=3.6
